vtt_builder/__init__.py
vtt_builder/_lowlevel.cpython-313t-i386-linux-musl.so
vtt_builder-0.5.0.dist-info/METADATA
vtt_builder-0.5.0.dist-info/WHEEL
vtt_builder.libs/libgcc_s-f5fcfe20.so.1
vtt_builder-0.5.0.dist-info/RECORD
