Metadata-Version: 2.4
Name: vtt-builder
Version: 0.5.0
Summary: Simple and fast functions for building WebVTT formatted transcripts.
Author-email: hello-world-bfree <hello-world-bfree@proton.me>
Requires-Python: >=3.8
